miseval/__init__.py
miseval/accuracy.py
miseval/auc.py
miseval/boundary_distance.py
miseval/confusion_matrix.py
miseval/core.py
miseval/dice.py
miseval/entropy.py
miseval/hausdorff.py
miseval/hinge.py
miseval/jaccard.py
miseval/kappa.py
miseval/mcc.py
miseval/precision.py
miseval/sensitivity.py
miseval/specificity.py
miseval/volumetric_similarity.py
tests/__init__.py
tests/test_accuracy.py
tests/test_auc.py
tests/test_boundary_distance.py
tests/test_confusion_matrix.py
tests/test_core.py
tests/test_dice.py
tests/test_edgecases.py
tests/test_entropy.py
tests/test_hausdorff.py
tests/test_hinge.py
tests/test_iou.py
tests/test_kappa.py
tests/test_mcc.py
tests/test_precision.py
tests/test_sensitivity.py
tests/test_specificity.py
tests/test_volumetric_similarity.py
miseval-1.3.0.dist-info/LICENSE.md
miseval-1.3.0.dist-info/METADATA
miseval-1.3.0.dist-info/WHEEL
miseval-1.3.0.dist-info/top_level.txt
miseval-1.3.0.dist-info/RECORD
