Metadata-Version: 2.1
Name: miseval
Version: 1.3.0
Summary: A Metric Library for Medical Image Segmentation Evaluation
Home-page: https://github.com/frankkramer-lab/miseval
Author: Dominik Müller
Author-email: dominik.mueller@informatik.uni-augsburg.de
License: GPLv3
Classifier: Programming Language :: Python :: 3
Classifier: Programming Language :: Python :: 3.8
Classifier: License :: OSI Approved :: GNU General Public License v3 (GPLv3)
Classifier: Operating System :: OS Independent
Classifier: Intended Audience :: Healthcare Industry
Classifier: Intended Audience :: Science/Research
Classifier: Topic :: Scientific/Engineering :: Artificial Intelligence
Classifier: Topic :: Scientific/Engineering :: Image Recognition
Classifier: Topic :: Scientific/Engineering :: Medical Science Apps.
Classifier: Topic :: Scientific/Engineering :: Mathematics
Requires-Python: >=3.8
License-File: LICENSE.md
Requires-Dist: numpy >=2.0
Requires-Dist: scikit-learn >=1.0.2
Requires-Dist: scikit-image >=0.19.1
Requires-Dist: scipy >=1.7.3
Requires-Dist: hausdorff >=0.2.6
Requires-Dist: numba
Requires-Dist: dictances >=1.5.3
